PyNLI/__init__.py
PyNLI/agent.py
PyNLI/config.py
PyNLI/extraction.py
PyNLI/main.py
PyNLI/messages.py
PyNLI/prompts.py
PyNLI/sessions.py
PyNLI/solara_interface.py
PyNLI/tools.py
Py2NL-0.1.8.dist-info/LICENSE
Py2NL-0.1.8.dist-info/METADATA
Py2NL-0.1.8.dist-info/WHEEL
Py2NL-0.1.8.dist-info/top_level.txt
Py2NL-0.1.8.dist-info/RECORD
