Metadata-Version: 2.1
Name: Py2NL
Version: 0.1.8
Summary: A natural language interface for Python
Home-page: https://github.com/TsXTatzumi/PyNLI
Author: Simeon Quant
Author-email: K51831785@students.jku.at
License: BSD 2-clause
Classifier: Development Status :: 3 - Alpha
Classifier: Intended Audience :: Science/Research
Classifier: License :: OSI Approved :: BSD License
Classifier: Framework :: Jupyter
Classifier: Programming Language :: Python :: 3.10
License-File: LICENSE
Requires-Dist: langchain ~=0.2.10
Requires-Dist: langchain-openai ~=0.1.8
Requires-Dist: langchain-community ~=0.2.9
Requires-Dist: langchain-experimental ~=0.0.49
Requires-Dist: solara ~=1.35.1
Requires-Dist: pandas
Requires-Dist: opencv-python
Requires-Dist: Pillow
Requires-Dist: pydantic ~=2.7.0
Requires-Dist: libcst ~=1.3.1
Requires-Dist: markdown ~=3.6
Requires-Dist: colorama ==0.4.6
Requires-Dist: pathlib
